setup.py
shinkenplugins/__init__.py
shinkenplugins.plugins.drupal_extensions.egg-info/PKG-INFO
shinkenplugins.plugins.drupal_extensions.egg-info/SOURCES.txt
shinkenplugins.plugins.drupal_extensions.egg-info/dependency_links.txt
shinkenplugins.plugins.drupal_extensions.egg-info/entry_points.txt
shinkenplugins.plugins.drupal_extensions.egg-info/namespace_packages.txt
shinkenplugins.plugins.drupal_extensions.egg-info/requires.txt
shinkenplugins.plugins.drupal_extensions.egg-info/top_level.txt
shinkenplugins/plugins/__init__.py
shinkenplugins/plugins/drupal_extensions/__init__.py
shinkenplugins/plugins/drupal_extensions/drupal_extensions.py